hookme/__init__.py
hookme/automated_webhook.py
hookme/d_webhook.py
hookme/exceptions.py
hookme/scheduler.py
hookme-0.1.9.dist-info/METADATA
hookme-0.1.9.dist-info/WHEEL
hookme-0.1.9.dist-info/top_level.txt
hookme-0.1.9.dist-info/RECORD
